<odoo>

  <!-- Detraccion en el Proveedor -->
  <record id="detraccino_form_view_proveedor" model="ir.ui.view">
    <field name="name">detraccion.form.proveedor</field>
    <field name="model">res.partner</field>
    <field name="inherit_id" ref="base.view_partner_form"/>
    <field name="arch" type="xml">
      <field name="vat" position="after">
        <field string="Detraccion" name="detrac_id"/>
      </field>
    </field>
  </record>

  <!-- Factura Cliente
  <record id="detraccino_form_view_factura" model="ir.ui.view">
    <field name="name">detraccion.form.factura</field>
    <field name="model">account.invoice</field>
    <field name="inherit_id" ref="account.invoice_form"/>
    <field name="arch" type="xml">
      <field name="payment_term_id" position="after">
        <field string="Detraccion" name="detrac_id" attrs="{'readonly':[['state','not in',['draft']]]}"/>
      </field>
    </field>
  </record>
  <!  -->

  <!-- Factura Proveedor -->
  <record id="detraccino_form_view_factura" model="ir.ui.view">
    <field name="name">detraccion.form.factura</field>
    <field name="model">account.invoice</field>
    <field name="inherit_id" ref="account.invoice_supplier_form"/>
    <field name="arch" type="xml">
      <field name="reference" position="after">
        <field string="Detraccion" name="detrac_id" attrs="{'readonly':[['state','not in',['draft']]]}"/>
      </field>
    </field>
  </record>

</odoo>